envstream/__init__.py
envstream/core.py
envstream-0.2.0.dist-info/METADATA
envstream-0.2.0.dist-info/WHEEL
envstream-0.2.0.dist-info/top_level.txt
envstream-0.2.0.dist-info/RECORD
