Metadata-Version: 2.4
Name: envstream
Version: 0.2.0
Summary: Live, database-backed environment variable manager for Python
Author-email: Matt Sullivan <mattys940@gmail.com>
License: MIT
Project-URL: Homepage, https://github.com/mjsully/envstream
Project-URL: Repository, https://github.com/yourusername/envstream
Requires-Python: >=3.7
